load_config.py
load_config/__init__.py
load_config/constants.py
load_config/custom_yaml.py
load_config/default_filepath.py
load_config/load_config.py
load_config-0.1.3b5.dist-info/LICENSE
load_config-0.1.3b5.dist-info/METADATA
load_config-0.1.3b5.dist-info/WHEEL
load_config-0.1.3b5.dist-info/top_level.txt
load_config-0.1.3b5.dist-info/RECORD
